mlcompare/__init__.py
mlcompare/inference.py
mlcompare/params_reader.py
mlcompare/pipelines.py
mlcompare/processing.py
mlcompare/results_writer.py
mlcompare/data/__init__.py
mlcompare/data/dataset_processor.py
mlcompare/data/datasets.py
mlcompare/data/split_data.py
mlcompare/models/__init__.py
mlcompare/models/models.py
mlcompare-1.2.2.dist-info/METADATA
mlcompare-1.2.2.dist-info/WHEEL
mlcompare-1.2.2.dist-info/licenses/LICENSE.txt
mlcompare-1.2.2.dist-info/RECORD
